ws2812/__init__.py
pyws2812-0.1.2.dist-info/LICENSE
pyws2812-0.1.2.dist-info/METADATA
pyws2812-0.1.2.dist-info/WHEEL
pyws2812-0.1.2.dist-info/top_level.txt
pyws2812-0.1.2.dist-info/RECORD
