Metadata-Version: 2.1
Name: pyws2812
Version: 0.1.2
Summary: A small example package
Home-page: https://github.com/phoenixsfly/pyWS2812
Author: xf_zhan
Author-email: zxf9972009@qq.com
License: MIT License
Platform: all
Classifier: Intended Audience :: Developers
Classifier: Operating System :: OS Independent
Classifier: Natural Language :: Chinese (Simplified)
Classifier: Programming Language :: Python :: 3
Classifier: Topic :: Software Development :: Libraries
License-File: LICENSE
Requires-Dist: pyserial
